hutil/__init__.py
hutil/_version.py
hutil/common.py
hutil/detection.py
hutil/functools.py
hutil/inference.py
hutil/loss.py
hutil/rnn.py
hutil/_C/__init__.py
hutil/_C/detection.cpython-37m-darwin.so
hutil/data/__init__.py
hutil/datasets/__init__.py
hutil/datasets/captcha.py
hutil/datasets/coco.py
hutil/datasets/svhn.py
hutil/datasets/voc.py
hutil/ext/__init__.py
hutil/ext/captcha.py
hutil/ext/checkpoint.py
hutil/ext/summary.py
hutil/train/__init__.py
hutil/train/_utils.py
hutil/train/gan_trainer.py
hutil/train/metrics.py
hutil/train/trainer.py
hutil/transforms/__init__.py
hutil/transforms/detection/__init__.py
hutil/transforms/detection/functional.py
hutil/transforms/segmentation/__init__.py
pytorch_hrvvi_ext-1.4.14.dist-info/METADATA
pytorch_hrvvi_ext-1.4.14.dist-info/RECORD
pytorch_hrvvi_ext-1.4.14.dist-info/WHEEL
pytorch_hrvvi_ext-1.4.14.dist-info/top_level.txt
