Metadata-Version: 2.1
Name: pytorch-hrvvi-ext
Version: 1.4.14
Summary: HrvvI's extension to PyTorch
Home-page: https://github.com/sbl1996/pytorch-hrvvi-ext
Author: HrvvI
Author-email: sbl1996@126.com
License: MIT
Platform: UNKNOWN
Classifier: License :: OSI Approved :: MIT License
Classifier: Programming Language :: Python
Classifier: Programming Language :: Python :: 3
Classifier: Programming Language :: Python :: Implementation :: CPython
Requires-Python: >=3.6.0
Provides-Extra: coco
Requires-Dist: torch
Requires-Dist: bidict
Requires-Dist: tqdm
Requires-Dist: arrow
Requires-Dist: itchat
Requires-Dist: nltk
Requires-Dist: toolz
Requires-Dist: pytorch-ignite
Requires-Dist: Pillow (>5.0.0)
Requires-Dist: xmltodict
Requires-Dist: torchvision
Requires-Dist: googledrivedownloader
Provides-Extra: coco
Requires-Dist: pycocotools; extra == 'coco'
